NFA_Aerosol/Instrument_Lib.py
NFA_Aerosol/Plot_Lib.py
NFA_Aerosol/Utility_Lib.py
NFA_Aerosol/__init__.py
NFA_Aerosol-1.3.0.dist-info/LICENSE.txt
NFA_Aerosol-1.3.0.dist-info/METADATA
NFA_Aerosol-1.3.0.dist-info/WHEEL
NFA_Aerosol-1.3.0.dist-info/top_level.txt
NFA_Aerosol-1.3.0.dist-info/RECORD
