Metadata-Version: 2.2
Name: NFA_Aerosol
Version: 1.3.0
Summary: Data handling for Aerosol Instruments at NFA
Author: NRCWE community
Project-URL: Homepage, https://github.com/NRCWE/NFA_Aerosol
Keywords: Aerosol,Particle,Instrument,Gas Analyzer,Dust,data analysis,numpy,python,scipy
Classifier: Programming Language :: Python :: 3
Classifier: License :: OSI Approved :: MIT License
Classifier: Operating System :: OS Independent
Requires-Python: >=3.8
License-File: LICENSE.txt
Requires-Dist: matplotlib>=3.1.3
Requires-Dist: numpy>=1.20.0
Requires-Dist: scipy>=1.5.0
Requires-Dist: pandas>=1.5.3
